d3ploy/__init__.py
d3ploy/d3ploy.py
d3ploy-4.4.2.dist-info/METADATA
d3ploy-4.4.2.dist-info/WHEEL
d3ploy-4.4.2.dist-info/entry_points.txt
d3ploy-4.4.2.dist-info/licenses/LICENSE
d3ploy-4.4.2.dist-info/RECORD
