Metadata-Version: 2.3
Name: d3ploy
Version: 4.4.2
Summary: Easily deploy to S3 with multiple environment support.
Project-URL: homepage, https://github.com/dryan/d3ploy
Project-URL: repository, https://github.com/dryan/d3ploy
Project-URL: documentation, https://github.com/dryan/d3ploy#readme
Author-email: dryan <dryan@users.noreply.github.com>
Classifier: Intended Audience :: Developers
Classifier: License :: OSI Approved :: MIT License
Classifier: Programming Language :: Python :: 3
Classifier: Programming Language :: Python :: 3.9
Classifier: Programming Language :: Python :: 3.10
Classifier: Programming Language :: Python :: 3.11
Classifier: Programming Language :: Python :: 3.12
Classifier: Programming Language :: Python :: 3.13
Requires-Python: >=3.11
Requires-Dist: boto3>=1.35.58
Requires-Dist: colorama>=0.4.6
Requires-Dist: packaging>=24.2
Requires-Dist: pathspec>=0.12.1
Requires-Dist: tqdm>=4.67.0
